pypostalwin.py
pypostalwin-0.0.3.dist-info/LICENSE
pypostalwin-0.0.3.dist-info/METADATA
pypostalwin-0.0.3.dist-info/WHEEL
pypostalwin-0.0.3.dist-info/top_level.txt
pypostalwin-0.0.3.dist-info/RECORD
