Metadata-Version: 2.1
Name: pypostalwin
Version: 0.0.3
Summary: python package for libpostal wrapper only for windows
Home-page: https://github.com/selva221724/pypostalwin
Author: Tamil Selvan A V
License: MIT
Platform: UNKNOWN
Classifier: Programming Language :: Python :: 3
Classifier: License :: OSI Approved :: MIT License
Classifier: Framework :: IPython
Classifier: Operating System :: Microsoft :: Windows :: Windows 10
Classifier: Intended Audience :: Science/Research
Classifier: Intended Audience :: Developers
Classifier: Topic :: Scientific/Engineering
Classifier: Environment :: Console
Requires-Python: >=3.6
License-File: LICENSE
